qdyhgq_linuxmcp_musicpro/__init__.py
qdyhgq_linuxmcp_musicpro-0.1.0.dist-info/METADATA
qdyhgq_linuxmcp_musicpro-0.1.0.dist-info/WHEEL
qdyhgq_linuxmcp_musicpro-0.1.0.dist-info/entry_points.txt
qdyhgq_linuxmcp_musicpro-0.1.0.dist-info/RECORD
