Metadata-Version: 2.4
Name: qdyhgq-linuxmcp-musicpro
Version: 0.1.0
Summary: Add your description here
Author-email: chablino <hewei274@outlook.com>
Requires-Python: >=3.13
Requires-Dist: mcp[cli]>=1.9.3
Requires-Dist: pygame>=2.6.1
Requires-Dist: requests>=2.32.3
